webullpaysdkquotescore/__init__.py
webullpaysdkquotescore/default_retry_policy.py
webullpaysdkquotescore/exceptions.py
webullpaysdkquotescore/quotes_client.py
webullpaysdkquotescore/quotes_decoder.py
webullpaysdkquotescore/quotes_payload_decoder.py
webullpaysdkquotescore/quotes_topic.py
webullpaysdkquotescore/grpc/__init__.py
webullpaysdkquotescore/grpc/connect.py
webullpaysdkquotescore/grpc/connect_status.py
webullpaysdkquotescore/grpc/core.py
webullpaysdkquotescore/grpc/error.py
webullpaysdkquotescore/grpc/grpc_client.py
webullpaysdkquotescore/grpc/grpc_retry_policy.py
webullpaysdkquotescore/grpc/grpc_signature_composer.py
webullpaysdkquotescore/grpc/msg.py
webullpaysdkquotescore/grpc/retry.py
webullpaysdkquotescore/grpc/pb/__init__.py
webullpaysdkquotescore/grpc/pb/gateway_pb2.py
webullpaysdkquotescore/grpc/pb/gateway_pb2_grpc.py
webullpaysdkquotescore/grpc/proto/__init__.py
webullpaysdkquotescore/grpc/task/__init__.py
webullpaysdkquotescore/grpc/task/task_timer.py
webullpay_python_sdk_quotes_core-0.1.0.dist-info/METADATA
webullpay_python_sdk_quotes_core-0.1.0.dist-info/WHEEL
webullpay_python_sdk_quotes_core-0.1.0.dist-info/top_level.txt
webullpay_python_sdk_quotes_core-0.1.0.dist-info/RECORD
