Metadata-Version: 2.4
Name: webullpay-python-sdk-quotes-core
Version: 0.1.0
Summary: The quotes core module of Webullpay Python SDK.
Home-page: 
Author: Webullpay
Author-email: 
License: Apache License 2.0
Platform: any
Requires-Dist: paho-mqtt==1.6.1
Requires-Dist: grpcio==1.70.0
Requires-Dist: grpcio-tools==1.70.0
Requires-Dist: protobuf==5.29.3
Requires-Dist: webullpay-python-sdk-core==0.1.0
Dynamic: author
Dynamic: description-content-type
Dynamic: license
Dynamic: platform
Dynamic: requires-dist
Dynamic: summary
